{
"type": "FeatureCollection",
"name": "crns_locations",
"crs": { "type": "name", "properties": { "name": "urn:ogc:def:crs:OGC:1.3:CRS84" } },
"features": [
{ "type": "Feature", "properties": { "id": 1, "inst": "FZJ", "soilnetid": 75 }, "geometry": { "type": "Point", "coordinates": [ 6.333016999781636, 50.50348700013167 ] } },
{ "type": "Feature", "properties": { "id": 2, "inst": "FZJ", "soilnetid": 0 }, "geometry": { "type": "Point", "coordinates": [ 6.33092000009407, 50.50490000001102 ] } },
{ "type": "Feature", "properties": { "id": 3, "inst": "FZJ", "soilnetid": 95 }, "geometry": { "type": "Point", "coordinates": [ 6.336067999851591, 50.503072999804829 ] } },
{ "type": "Feature", "properties": { "id": 4, "inst": "FZJ", "soilnetid": 13 }, "geometry": { "type": "Point", "coordinates": [ 6.3298118333778, 50.503840953722289 ] } },
{ "type": "Feature", "properties": { "id": 5, "inst": "FZJ", "soilnetid": 36 }, "geometry": { "type": "Point", "coordinates": [ 6.331498815520929, 50.5027871998183 ] } },
{ "type": "Feature", "properties": { "id": 6, "inst": "FZJ", "soilnetid": 0 }, "geometry": { "type": "Point", "coordinates": [ 6.329248482638009, 50.501488140717065 ] } },
{ "type": "Feature", "properties": { "id": 7, "inst": "UP", "soilnetid": 118 }, "geometry": { "type": "Point", "coordinates": [ 6.338301197699129, 50.502345420135384 ] } },
{ "type": "Feature", "properties": { "id": 8, "inst": "UP", "soilnetid": 65 }, "geometry": { "type": "Point", "coordinates": [ 6.333411083116973, 50.50429942504055 ] } },
{ "type": "Feature", "properties": { "id": 9, "inst": "UP", "soilnetid": 67 }, "geometry": { "type": "Point", "coordinates": [ 6.335433429714622, 50.503988471241939 ] } },
{ "type": "Feature", "properties": { "id": 10, "inst": "KIT", "soilnetid": 122 }, "geometry": { "type": "Point", "coordinates": [ 6.331464271511877, 50.501745751002787 ] } },
{ "type": "Feature", "properties": { "id": 11, "inst": "KIT", "soilnetid": 142 }, "geometry": { "type": "Point", "coordinates": [ 6.3333272047918, 50.501216719146626 ] } },
{ "type": "Feature", "properties": { "id": 12, "inst": "GFZ", "soilnetid": 100 }, "geometry": { "type": "Point", "coordinates": [ 6.328229328163307, 50.502828129535807 ] } },
{ "type": "Feature", "properties": { "id": 13, "inst": "GFZ", "soilnetid": 133 }, "geometry": { "type": "Point", "coordinates": [ 6.335803970591999, 50.501688194015962 ] } },
{ "type": "Feature", "properties": { "id": 14, "inst": "GFZ", "soilnetid": 49 }, "geometry": { "type": "Point", "coordinates": [ 6.333979977982002, 50.50222669761596 ] } },
{ "type": "Feature", "properties": { "id": 15, "inst": "UH\/UFZ", "soilnetid": 148 }, "geometry": { "type": "Point", "coordinates": [ 6.335934618671759, 50.50121465633147 ] } }
]
}
